ensembl_rest/__init__.py
ensembl_rest/assemblymapper.py
ensembl_rest/ensemblclient.py
ensembl_rest/utils.py
ensembl_rest/core/__init__.py
ensembl_rest/core/baseclient.py
ensembl_rest/core/restclient.py
ensembl_rest/data/__init__.py
ensembl_rest/data/ensembl_response_codes.json
ensembl_rest/data/ensembl_rest_endpoints.json
ensembl_rest-0.3.4.dist-info/LICENSE
ensembl_rest-0.3.4.dist-info/METADATA
ensembl_rest-0.3.4.dist-info/WHEEL
ensembl_rest-0.3.4.dist-info/top_level.txt
ensembl_rest-0.3.4.dist-info/RECORD
