Metadata-Version: 2.1
Name: ensembl-rest
Version: 0.3.4
Summary: An interface to the Ensembl REST APIs, biological data at your fingertips.
Home-page: https://github.com/Ad115/EnsemblRest
Author: Ad115
Author-email: a.garcia230395@gmail.com
Project-URL: Say Thanks!, https://saythanks.io/to/Ad115
Project-URL: Documentation, https://ensemblrest.readthedocs.io
Project-URL: Author, https://agargar.wordpress.com/
Keywords: ensembl rest api client genomes
Classifier: Development Status :: 3 - Alpha
Classifier: Intended Audience :: Information Technology
Classifier: Intended Audience :: Science/Research
Classifier: Intended Audience :: Education
Classifier: Intended Audience :: Developers
Classifier: Topic :: Scientific/Engineering :: Artificial Life
Classifier: Topic :: Scientific/Engineering :: Bio-Informatics
Classifier: Topic :: Scientific/Engineering :: Medical Science Apps.
Classifier: License :: OSI Approved :: MIT License
Classifier: Programming Language :: Python :: 3 :: Only
License-File: LICENSE
Requires-Dist: importlib-resources
Requires-Dist: requests
Requires-Dist: simplejson
Requires-Dist: intervaltree
Provides-Extra: dev
Requires-Dist: jupyter ; extra == 'dev'
Requires-Dist: scrapy ; extra == 'dev'
